MANIFEST.in
README.md
setup.py
sentry_nameko/__init__.py
sentry_nameko/interface.py
sentry_nameko.egg-info/PKG-INFO
sentry_nameko.egg-info/SOURCES.txt
sentry_nameko.egg-info/dependency_links.txt
sentry_nameko.egg-info/entry_points.txt
sentry_nameko.egg-info/not-zip-safe
sentry_nameko.egg-info/top_level.txt
sentry_nameko/templates/sentry_nameko/call_id_stack.html