Metadata-Version: 1.1
Name: sentry-nameko
Version: 0.1.2
Summary: Integration helpers for Sentry and Nameko
Home-page: http://github.com/onefinestay/sentry-nameko
Author: onefinestay
Author-email: engineering@onefinestay.com
License: Apache License, Version 2.0
Platform: UNKNOWN
Classifier: Programming Language :: Python
Classifier: Operating System :: MacOS :: MacOS X
Classifier: Operating System :: POSIX
Classifier: Programming Language :: Python :: 2.7
Classifier: Topic :: Internet
Classifier: Topic :: Software Development :: Libraries :: Python Modules
Classifier: Intended Audience :: Developers
Requires: sentry
